tuya_vacuum/__init__.py
tuya_vacuum/const.py
tuya_vacuum/errors.py
tuya_vacuum/lz4.py
tuya_vacuum/tuya.py
tuya_vacuum/utils.py
tuya_vacuum/vacuum.py
tuya_vacuum/map/__init__.py
tuya_vacuum/map/layout.py
tuya_vacuum/map/map.py
tuya_vacuum/map/path.py
tuya_vacuum/map/room.py
tuya_vacuum-0.1.9.dist-info/METADATA
tuya_vacuum-0.1.9.dist-info/WHEEL
tuya_vacuum-0.1.9.dist-info/licenses/LICENSE
tuya_vacuum-0.1.9.dist-info/RECORD
