Metadata-Version: 2.3
Name: tuya-vacuum
Version: 0.1.9
Summary: A python library to view maps from Tuya robot vacuums
Project-URL: Homepage, https://github.com/jaidenlabelle/tuya-vacuum
Project-URL: Issues, https://github.com/jaidenlabelle/tuya-vacuum/issues
Author-email: Jaiden Labelle <jaidenjlabelle@gmail.com>
Classifier: License :: OSI Approved :: MIT License
Classifier: Operating System :: OS Independent
Classifier: Programming Language :: Python :: 3
Requires-Python: >=3.6
